[
  {
    "id": "cascanueces",
    "title": "Barbie en el Cascanueces",
    "year": 2001,
    "playlist": "Barbie Clásicas",
    "poster": "img/posters/nutcracker.jpg",
    "players": [
      { "label": "Ver", "url": "https://cuevana3.rs/pelicula/barbie-en-el-cascanueces" }
    ]
  },
  {
    "id": "rapunzel",
    "title": "Barbie como Rapunzel",
    "year": 2002,
    "playlist": "Barbie Clásicas",
    "poster": "img/posters/rapunzel.jpg",
    "players": [
      { "label": "Ver", "url": "https://advertape.net/v/D2LrGWbWR4uBKq" }
    ]
  },
  {
    "id": "lago-cisnes",
    "title": "Barbie en el Lago de los Cisnes",
    "year": 2003,
    "playlist": "Barbie Clásicas",
    "poster": "img/posters/swanlake.jpg",
    "players": [
      { "label": "Ver", "url": "https://cuevana3.rs/pelicula/barbie-en-el-lago-de-los-cisnes" }
    ]
  },
  {
    "id": "princesa-plebeya",
    "title": "Barbie: La princesa y la plebeya",
    "year": 2004,
    "playlist": "Barbie Clásicas",
    "poster": "img/posters/princessandpauper.jpg",
    "players": [
      { "label": "Ver", "url": "https://stre4mpay.one/dbgp611xq5fx" }
    ]
  },
  {
    "id": "fairytopia",
    "title": "Barbie Fairytopia",
    "year": 2005,
    "playlist": "Fairytopia",
    "poster": "img/posters/fairytopia.jpg",
    "players": [
      { "label": "Ver", "url": "https://stre4mpay.one/jyugkjw9imwk" }
    ]
  },
  {
    "id": "pegaso",
    "title": "Barbie y la magia de Pegaso",
    "year": 2005,
    "playlist": "Barbie Clásicas",
    "poster": "img/posters/pegasus.jpg",
    "players": [
      { "label": "Ver", "url": "https://cuevana3.rs/pelicula/barbie-y-la-magia-de-pegaso" }
    ]
  },
  {
    "id": "mermaidia",
    "title": "Barbie Fairytopia: Mermaidia",
    "year": 2006,
    "playlist": "Fairytopia",
    "poster": "img/posters/mermaidia.jpg",
    "players": [
      { "label": "Ver", "url": "https://advertape.net/v/d83lb8zXRgSkwYx" }
    ]
  },
  {
    "id": "12-princesas",
    "title": "Barbie en las 12 princesas bailarinas",
    "year": 2006,
    "playlist": "Princesas",
    "poster": "img/posters/12princesses.jpg",
    "players": [
      { "label": "Ver", "url": "https://cuevana3.rs/pelicula/barbie-en-las-12-princesas-bailarinas" }
    ]
  },
  {
    "id": "arco-iris",
    "title": "Barbie Fairytopia: La magia del arco iris",
    "year": 2007,
    "playlist": "Fairytopia",
    "poster": "img/posters/rainbowmagic.jpg",
    "players": [
      { "label": "Ver", "url": "https://stre4mpay.one/of924pet99t4" }
    ]
  },
  {
    "id": "princesa-isla",
    "title": "Barbie como la princesa de los animales",
    "year": 2007,
    "playlist": "Princesas",
    "poster": "img/posters/islandprincess.jpg",
    "players": [
      { "label": "Ver", "url": "https://advertape.net/v/AAlxovaDP7FBwp" }
    ]
  },
  {
    "id": "mariposa",
    "title": "Barbie Mariposa",
    "year": 2008,
    "playlist": "Fairytopia",
    "poster": "img/posters/mariposa.jpg",
    "players": [
      { "label": "Ver", "url": "https://cuevana3.rs/pelicula/barbie-mariposa" }
    ]
  },
  {
    "id": "castillo-diamantes",
    "title": "Barbie y el castillo de diamantes",
    "year": 2008,
    "playlist": "Princesas",
    "poster": "img/posters/diamondcastle.jpg",
    "players": [
      { "label": "Ver", "url": "https://cuevana3.rs/pelicula/barbie-y-el-castillo-de-diamantes" }
    ]
  },
  {
    "id": "cuento-navidad",
    "title": "Barbie en Cuento de Navidad",
    "year": 2008,
    "playlist": "Barbie Clásicas",
    "poster": "img/posters/christmascarol.jpg",
    "players": [
      { "label": "Ver", "url": "https://cuevana3.rs/pelicula/barbie-en-cuento-de-navidad" }
    ]
  },
  {
    "id": "pulgarcita",
    "title": "Barbie Pulgarcita",
    "year": 2009,
    "playlist": "Barbie Clásicas",
    "poster": "img/posters/thumbelina.jpg",
    "players": [
      { "label": "Ver", "url": "https://powcloub.org/ixkdclod53i4" }
    ]
  },
  {
    "id": "tres-mosqueteras",
    "title": "Barbie y las tres mosqueteras",
    "year": 2009,
    "playlist": "Barbie Clásicas",
    "poster": "img/posters/3musketeers.jpg",
    "players": [
      { "label": "Ver", "url": "https://stre4mpay.one/17q2oe3nn56z" }
    ]
  },
  {
    "id": "aventura-moda",
    "title": "Barbie en una aventura de moda",
    "year": 2010,
    "playlist": "Era Moderna",
    "poster": "img/posters/fashionfairytale.jpg",
    "players": [
      { "label": "Ver", "url": "https://advertape.net/v/ydamXYvxe7I1LaV" }
    ]
  },
  {
    "id": "sirenas-1",
    "title": "Barbie: Una aventura de sirenas",
    "year": 2010,
    "playlist": "Sirenas",
    "poster": "img/posters/mermaidtale.jpg",
    "players": [
      { "label": "Ver", "url": "https://filemoon.sx/d/lcyq30qeu0hc" }
    ]
  },
  {
    "id": "secreto-hadas",
    "title": "Barbie y el secreto de las hadas",
    "year": 2011,
    "playlist": "Era Moderna",
    "poster": "img/posters/fairysecret.jpg",
    "players": [
      { "label": "Ver", "url": "https://cuevana3.rs/pelicula/barbie-el-secreto-de-las-hadas" }
    ]
  },
  {
    "id": "escuela-princesas",
    "title": "Barbie: Escuela de princesas",
    "year": 2011,
    "playlist": "Princesas",
    "poster": "img/posters/princesscharm.jpg",
    "players": [
      { "label": "Ver", "url": "https://stre4mpay.one/kd6j16gf4nw9" }
    ]
  },
  {
    "id": "sirenas-2",
    "title": "Barbie: Una aventura de sirenas 2",
    "year": 2012,
    "playlist": "Sirenas",
    "poster": "img/posters/mermaidtale2.jpg",
    "players": [
      { "label": "Ver", "url": "https://stre4mpay.one/6jx4wam06nb7" }
    ]
  },
  {
    "id": "princesa-cantante",
    "title": "Barbie: La princesa y la cantante",
    "year": 2012,
    "playlist": "Princesas",
    "poster": "img/posters/popstar.jpg",
    "players": [
      { "label": "Ver", "url": "https://cuevana3.rs/pelicula/barbie-la-princesa-y-la-cantante" }
    ]
  },
  {
    "id": "bailarina-magica",
    "title": "Barbie en la bailarina mágica",
    "year": 2013,
    "playlist": "Princesas",
    "poster": "img/posters/pinkshoes.jpg",
    "players": [
      { "label": "Ver", "url": "https://cuevana3.rs/pelicula/barbie-en-la-bailarina-magica" }
    ]
  },
  {
    "id": "mariposa-princesa-hadas",
    "title": "Barbie Mariposa y la princesa de las hadas",
    "year": 2013,
    "playlist": "Fairytopia",
    "poster": "img/posters/mariposa2.jpg",
    "players": [
      { "label": "Ver", "url": "https://cuevana3.rs/pelicula/barbie-mariposa-y-la-princesa-de-las-hadas" }
    ]
  },
  {
    "id": "princesa-perlas",
    "title": "Barbie: La princesa de las perlas",
    "year": 2014,
    "playlist": "Princesas",
    "poster": "img/posters/pearlprincess.jpg",
    "players": [
      { "label": "Ver", "url": "URL_AQUI" }
    ]
  },
  {
    "id": "puerta-secreta",
    "title": "Barbie y la puerta secreta",
    "year": 2014,
    "playlist": "Fairytopia",
    "poster": "img/posters/secretdoor.jpg",
    "players": [
      { "label": "Ver", "url": "https://stre4mpay.one/ismft7kffjo0" }
    ]
  }
]
